[
    {
        "id": 1,
        "nombre": "Ernesto Rafael Soda",
        "fecha_nacimiento": "1950-05-10",
        "padres": [],
        "hijos": [
            2
        ],
        "descripcion": "El humano más bueno.",
        "x": -100,
        "y": 0
    },
    {
        "id": 2,
        "nombre": "Irene María Juana Soda",
        "fecha_nacimiento": "1980-02-15",
        "padres": [
            1
        ],
        "hijos": [
            3
        ],
        "descripcion": "Aficionada a la pintura.",
        "x": 0,
        "y": 200
    },
    {
        "id": 3,
        "nombre": "Digna Susana Antonia Soda",
        "fecha_nacimiento": "2010-08-12",
        "padres": [
            2
        ],
        "hijos": [],
        "descripcion": "Le encanta dibujar.",
        "x": 100,
        "y": 400
    },
        {
        "id": 4,
        "nombre": "Diolinda Margarita Soda",
        "fecha_nacimiento": "2010-08-12",
        "padres": [
            2
        ],
        "hijos": [],
        "descripcion": "Le encanta dibujar.",
        "x": 100,
        "y": 400
    },
    {
        "id": 5,
        "nombre": "Hugo Pablo Ángel Soda",
        "fecha_nacimiento": "1975-03-20",
        "padres": [
            1
        ],
        "hijos": [],
        "descripcion": "Aficionado a la música.",
        "x": -200,
        "y": 100
    }
]